twovyper/__init__.py
twovyper/client.py
twovyper/config.py
twovyper/exceptions.py
twovyper/main.py
twovyper/utils.py
twovyper/vyper.py
twovyper/analysis/__init__.py
twovyper/analysis/analyzer.py
twovyper/analysis/heuristics.py
twovyper/analysis/structure_checker.py
twovyper/analysis/symbol_checker.py
twovyper/analysis/type_annotator.py
twovyper/ast/__init__.py
twovyper/ast/arithmetic.py
twovyper/ast/ast_nodes.py
twovyper/ast/interfaces.py
twovyper/ast/names.py
twovyper/ast/nodes.py
twovyper/ast/text.py
twovyper/ast/types.py
twovyper/ast/visitors.py
twovyper/backends/__init__.py
twovyper/backends/carbon.jar
twovyper/backends/silicon.jar
twovyper/backends/silver-sif-extension.jar
twovyper/parsing/__init__.py
twovyper/parsing/lark.py
twovyper/parsing/parser.py
twovyper/parsing/preprocessor.py
twovyper/parsing/transformer.py
twovyper/parsing/vyper_0_1.lark
twovyper/parsing/vyper_0_2.lark
twovyper/resources/__init__.py
twovyper/resources/all.vpr
twovyper/resources/array.vpr
twovyper/resources/blockchain.vpr
twovyper/resources/contract.vpr
twovyper/resources/convert.vpr
twovyper/resources/map.vpr
twovyper/resources/math.vpr
twovyper/resources/range.vpr
twovyper/resources/struct.vpr
twovyper/resources/verification.vpr
twovyper/resources/wrapped_integer.vpr
twovyper/translation/__init__.py
twovyper/translation/abstract.py
twovyper/translation/allocation.py
twovyper/translation/arithmetic.py
twovyper/translation/balance.py
twovyper/translation/context.py
twovyper/translation/expression.py
twovyper/translation/function.py
twovyper/translation/helpers.py
twovyper/translation/lemma.py
twovyper/translation/mangled.py
twovyper/translation/model.py
twovyper/translation/pure_function.py
twovyper/translation/pure_statement.py
twovyper/translation/pure_translators.py
twovyper/translation/resource.py
twovyper/translation/specification.py
twovyper/translation/state.py
twovyper/translation/statement.py
twovyper/translation/translator.py
twovyper/translation/type.py
2vyper-0.3.0.dist-info/LICENSE.txt
2vyper-0.3.0.dist-info/METADATA
2vyper-0.3.0.dist-info/WHEEL
2vyper-0.3.0.dist-info/entry_points.txt
2vyper-0.3.0.dist-info/top_level.txt
2vyper-0.3.0.dist-info/RECORD
