Metadata-Version: 2.1
Name: 2vyper
Version: 0.3.0
Summary: Static verifier for Vyper, based on Viper.
Home-page: http://www.pm.inf.ethz.ch/research/nagini.html
Author: Viper Team
Author-email: viper@inf.ethz.ch
License: MPL-2.0
Platform: UNKNOWN
Classifier: Development Status :: 4 - Beta
Classifier: Environment :: Console
Classifier: Intended Audience :: Developers
Classifier: License :: OSI Approved :: Mozilla Public License 2.0 (MPL 2.0)
Classifier: Operating System :: OS Independent
Classifier: Programming Language :: Python :: 3 :: Only
Classifier: Topic :: Software Development
Requires-Dist: jpype1 (==0.7.0)
Requires-Dist: lark-parser (>=0.8.1)
Requires-Dist: vyper (==0.1.0b16)
Requires-Dist: vvm (==0.1.0)
Requires-Dist: z3-solver
